{
  "nav_bar": {
    "links": [
      { "content": "", "path": "/app" },
      { "content": "Dashboard", "path": "/app/dashboard" },
      { "content": "Widgets", "path": "/app/widgets" },
      { "content": "Settings", "path": "/app/settings" }
       
    ]
  },

  "plan_page": {
    "heading": "Welcome to Review Suite",
    "description": "We will automatically gather, analyse all the reviews and showcase the most compelling product reviews, turning satisfied customers into your most effective salespeople",
    "heading_2": "Select a Subscription plan to proceed",
    "free_plan_button": "Subscripe Now",
    "monthly_plan_button": "Subscripe Now",
    "monthly_plan_prefix": "$",
    "montly_plan_text": "/month",
    "yearly_plan_button": "Yearly Plan",
    "yearly_plan_prefix": "$",
    "yearly_plan_text": "/year",
    "img_src": "https://ik.imagekit.io/1tudtg11f/Group%201000006811.jpg?updatedAt=1716987244600"
  },
  "onboarding": {
    "heading_1": "Almost there, Lets dive in!",
    "description_1": "Unlock trust and credibility with authentic reviews. Your strategic partner Reviewsuite by your side",
    "img_1": "https://ik.imagekit.io/x3tjafdwm/ReviewSuite/Import.svg?updatedAt=1697097370177",
    "heading_2": "Import Reviews",
    "description_2": "We suggest you to keep it centralized. Import all your reviews ffrom other platforms right away",
    "button_1": "Import Now",
    "img_2": "https://ik.imagekit.io/x3tjafdwm/ReviewSuite/Explore.svg?updatedAt=1697097369554",
    "heading_3": "Get Started",
    "description_3": "Go ahead wit ReviewSuite, you can import your stores's exisiting reviews later at your convenience.",
    "button_2": "Get started",
    "button_3": "How do I use review suite",
    "modal_1_heading": "Choose Plan Navigate",
    "modal_1_description": "You are in free plan. Are you sure to continue in free plan with limited access (or) get more features with paid plan",
    "modal_1_button_1": "Limited Access",
    "modal_1_button_2": "Get More Features"
  } 
}
